cmem_plugin_graph_insights/__init__.py
cmem_plugin_graph_insights/update_snapshots.py
cmem_plugin_graph_insights/update_snapshots.svg
cmem_plugin_graph_insights-0.5.0.dist-info/METADATA
cmem_plugin_graph_insights-0.5.0.dist-info/WHEEL
cmem_plugin_graph_insights-0.5.0.dist-info/licenses/LICENSE
cmem_plugin_graph_insights-0.5.0.dist-info/RECORD
